vedro_profiling/__init__.py
vedro_profiling/_vedro_profiling.py
vedro_profiling/py.typed
vedro_profiling-0.1.2.data/data/vedro_profiling/py.typed
vedro_profiling-0.1.2.dist-info/METADATA
vedro_profiling-0.1.2.dist-info/WHEEL
vedro_profiling-0.1.2.dist-info/licenses/LICENSE.txt
vedro_profiling-0.1.2.dist-info/RECORD
