Metadata-Version: 2.4
Name: vedro-profiling
Version: 0.1.2
Summary: Plugin for Vedro framework for measuring resource usage of tests
Project-URL: Homepage, https://github.com/Lolimpo/vedro-profiling
Project-URL: Repository, https://github.com/Lolimpo/vedro-profiling
Author-email: Nikita Mikheev <thelol1mpo@gmail.com>
License: 
License-File: LICENSE.txt
Classifier: License :: OSI Approved :: Apache Software License
Classifier: Programming Language :: Python :: 3.10
Classifier: Programming Language :: Python :: 3.11
Classifier: Programming Language :: Python :: 3.12
Classifier: Programming Language :: Python :: 3.13
Classifier: Typing :: Typed
Requires-Python: >=3.10
Requires-Dist: docker<8.0.0,>=7.0.0
Requires-Dist: matplotlib<4.0.0,>=3.10.0
Requires-Dist: psutil<8.0.0,>=7.0.0
Requires-Dist: vedro<2.0.0,>=1.13.0
